{
  "ReRoutes": [
    {
      "DownstreamPathTemplate": "/api/{version}/{everything}",
      "DownstreamScheme": "http",
      "DownstreamHostAndPorts": [
        {
          "Host": "apartment.api",
          "Port": 80
        }
      ],
      "UpstreamPathTemplate": "/api/{version}/apartment/{everything}",
      "UpstreamHttpMethod": []
    },
    {
      "DownstreamPathTemplate": "/api/{version}/{everything}",
      "DownstreamScheme": "http",
      "DownstreamHostAndPorts": [
        {
          "Host": "villa.api",
          "Port": 80
        }
      ],
      "UpstreamPathTemplate": "/api/{version}/villa/{everything}",
      "UpstreamHttpMethod": []
    },
    {
      "DownstreamPathTemplate": "/api/{version}/{everything}",
      "DownstreamScheme": "http",
      "DownstreamHostAndPorts": [
        {
          "Host": "townhouse.api",
          "Port": 80
        }
      ],
      "UpstreamPathTemplate": "/api/{version}/townhouse/{everything}",
      "UpstreamHttpMethod": []
    },
    {
      "DownstreamPathTemplate": "/api/{version}/{everything}",
      "DownstreamScheme": "http",
      "DownstreamHostAndPorts": [
        {
          "Host": "penthouse.api",
          "Port": 80
        }
      ],
      "UpstreamPathTemplate": "/api/{version}/penthouse/{everything}",
      "UpstreamHttpMethod": []
    },
    {
      "DownstreamPathTemplate": "/api/{version}/{everything}",
      "DownstreamScheme": "http",
      "DownstreamHostAndPorts": [
        {
          "Host": "chalet.api",
          "Port": 80
        }
      ],
      "UpstreamPathTemplate": "/api/{version}/chalet/{everything}",
      "UpstreamHttpMethod": []
    },
    {
      "DownstreamPathTemplate": "/api/{version}/{everything}",
      "DownstreamScheme": "http",
      "DownstreamHostAndPorts": [
        {
          "Host": "twinhouse.api",
          "Port": 80
        }
      ],
      "UpstreamPathTemplate": "/api/{version}/twinhouse/{everything}",
      "UpstreamHttpMethod": []
    },
    {
      "DownstreamPathTemplate": "/api/{version}/{everything}",
      "DownstreamScheme": "http",
      "DownstreamHostAndPorts": [
        {
          "Host": "duplex.api",
          "Port": 80
        }
      ],
      "UpstreamPathTemplate": "/api/{version}/duplex/{everything}",
      "UpstreamHttpMethod": []
    },
    {
      "DownstreamPathTemplate": "/api/{version}/{everything}",
      "DownstreamScheme": "http",
      "DownstreamHostAndPorts": [
        {
          "Host": "fullfloor.api",
          "Port": 80
        }
      ],
      "UpstreamPathTemplate": "/api/{version}/fullfloor/{everything}",
      "UpstreamHttpMethod": []
    },
    {
      "DownstreamPathTemplate": "/api/{version}/{everything}",
      "DownstreamScheme": "http",
      "DownstreamHostAndPorts": [
        {
          "Host": "halffloor.api",
          "Port": 80
        }
      ],
      "UpstreamPathTemplate": "/api/{version}/halffloor/{everything}",
      "UpstreamHttpMethod": []
    },
    {
      "DownstreamPathTemplate": "/api/{version}/{everything}",
      "DownstreamScheme": "http",
      "DownstreamHostAndPorts": [
        {
          "Host": "wholebuilding.api",
          "Port": 80
        }
      ],
      "UpstreamPathTemplate": "/api/{version}/wholebuilding/{everything}",
      "UpstreamHttpMethod": []
    },
    {
      "DownstreamPathTemplate": "/api/{version}/{everything}",
      "DownstreamScheme": "http",
      "DownstreamHostAndPorts": [
        {
          "Host": "land.api",
          "Port": 80
        }
      ],
      "UpstreamPathTemplate": "/api/{version}/land/{everything}",
      "UpstreamHttpMethod": []
    },
    {
      "DownstreamPathTemplate": "/api/{version}/{everything}",
      "DownstreamScheme": "http",
      "DownstreamHostAndPorts": [
        {
          "Host": "bulksale.api",
          "Port": 80
        }
      ],
      "UpstreamPathTemplate": "/api/{version}/bulksale/{everything}",
      "UpstreamHttpMethod": []
    },
    {
      "DownstreamPathTemplate": "/api/{version}/{everything}",
      "DownstreamScheme": "http",
      "DownstreamHostAndPorts": [
        {
          "Host": "bungalows.api",
          "Port": 80
        }
      ],
      "UpstreamPathTemplate": "/api/{version}/bungalows/{everything}",
      "UpstreamHttpMethod": []
    },
    {
      "DownstreamPathTemplate": "/api/{version}/{everything}",
      "DownstreamScheme": "http",
      "DownstreamHostAndPorts": [
        {
          "Host": "hotelapartments.api",
          "Port": 80
        }
      ],
      "UpstreamPathTemplate": "/api/{version}/hotelapartments/{everything}",
      "UpstreamHttpMethod": []
    },
    {
      "DownstreamPathTemplate": "/api/{version}/{everything}",
      "DownstreamScheme": "http",
      "DownstreamHostAndPorts": [
        {
          "Host": "ivilla.api",
          "Port": 80
        }
      ],
      "UpstreamPathTemplate": "/api/{version}/ivilla/{everything}",
      "UpstreamHttpMethod": []
    }
  ],
  "GlobalConfiguration": {
    "RequestIdKey": "OcRequestId",
    "AdministrationPath": "/administration",
    "AuthenticationOptions": {
      "AuthenticationProviderKey": "U3@msP9a@57zmRqd42L",
      "AllowedScopes": []
    }
  }
}
  